UN8ID/__init__.py
UN8ID/prototype.py
UN8ID/utils/__init__.py
UN8ID/utils/getmac.py
UN8ID-0.0.3.dist-info/LICENSE
UN8ID-0.0.3.dist-info/METADATA
UN8ID-0.0.3.dist-info/WHEEL
UN8ID-0.0.3.dist-info/top_level.txt
UN8ID-0.0.3.dist-info/RECORD
