Metadata-Version: 2.2
Name: UN8ID
Version: 0.0.3
Summary: A Heavy Globally Unique Identifier (specification and prototype)
Author-email: "Adrian F. Hoefflin" <srccircumflex-un8id@outlook.com>
License: CC BY 4.0 Attribution 4.0 International
Project-URL: Homepage, https://github.com/UN8ID
Keywords: un8id,Universal Identifier,id,uid
Classifier: Intended Audience :: Developers
Classifier: Topic :: Security :: Cryptography
Requires-Python: >=3.10
License-File: LICENSE
